__init__.py
app360_toolkit/__init__.py
app360_toolkit/config/__init__.py
app360_toolkit/config/settings.py
app360_toolkit/core/__init__.py
app360_toolkit/core/discovery.py
app360_toolkit/core/registry.py
app360_toolkit/factories/__init__.py
app360_toolkit/factories/document_factory.py
app360_toolkit/factories/notification_factory.py
app360_toolkit/factories/settings.py
app360_toolkit/processors/__init__.py
app360_toolkit/processors/document/__init__.py
app360_toolkit/processors/document/cnpj.py
app360_toolkit/processors/document/cpf.py
app360_toolkit/processors/document/rg.py
app360_toolkit/processors/document/settings.py
app360_toolkit/processors/notification/__init__.py
app360_toolkit/processors/notification/settings.py
app360_toolkit-0.1.0.dist-info/licenses/LICENSE
app360_toolkit-0.1.0.dist-info/METADATA
app360_toolkit-0.1.0.dist-info/WHEEL
app360_toolkit-0.1.0.dist-info/top_level.txt
app360_toolkit-0.1.0.dist-info/RECORD
