Metadata-Version: 2.4
Name: app360-toolkit
Version: 0.1.0
Summary: A comprehensive Python toolkit for rapid development, document validation, and utilities.
Author-email: Sergius Fortuna <sfortuna1977@gmail.com>
License: MIT
Project-URL: Homepage, https://github.com/sfortuna77/app360-toolkit
Project-URL: Repository, https://github.com/sfortuna77/app360-toolkit
Project-URL: Issues, https://github.com/sfortuna77/app360-toolkit/issues
Project-URL: Documentation, https://github.com/sfortuna77/app360-toolkit#readme
Keywords: python,toolkit,validation,cpf,cnpj,brazilian-documents,factory-pattern,utilities
Classifier: Development Status :: 4 - Beta
Classifier: Intended Audience :: Developers
Classifier: License :: OSI Approved :: MIT License
Classifier: Operating System :: OS Independent
Classifier: Programming Language :: Python :: 3
Classifier: Programming Language :: Python :: 3.8
Classifier: Programming Language :: Python :: 3.9
Classifier: Programming Language :: Python :: 3.10
Classifier: Programming Language :: Python :: 3.11
Classifier: Programming Language :: Python :: 3.12
Requires-Python: >=3.8
License-File: LICENSE
Provides-Extra: dev
Requires-Dist: pytest>=6.0; extra == "dev"
Requires-Dist: black>=21.0; extra == "dev"
Requires-Dist: flake8>=3.8; extra == "dev"
Requires-Dist: mypy>=0.800; extra == "dev"
Requires-Dist: pre-commit>=2.15.0; extra == "dev"
Provides-Extra: test
Requires-Dist: pytest>=6.0; extra == "test"
Requires-Dist: pytest-cov>=3.0; extra == "test"
Requires-Dist: coverage>=6.0; extra == "test"
Provides-Extra: docs
Requires-Dist: sphinx>=4.0; extra == "docs"
Requires-Dist: sphinx-rtd-theme>=1.0; extra == "docs"
Dynamic: license-file
